python_arango_ogm/__init__.py
python_arango_ogm/cli/pao_migrate.py
python_arango_ogm/db/pao_database.py
python_arango_ogm/db/pao_db_base.py
python_arango_ogm/db/pao_edges.py
python_arango_ogm/db/pao_fields.py
python_arango_ogm/db/pao_indexes.py
python_arango_ogm/db/pao_migration_builder.py
python_arango_ogm/db/pao_migration_model.py
python_arango_ogm/db/pao_migrator.py
python_arango_ogm/db/pao_model.py
python_arango_ogm/db/pao_model_discovery.py
python_arango_ogm/db/pao_queries.py
python_arango_ogm/db/tests/__init__.py
python_arango_ogm/db/tests/database.py
python_arango_ogm/db/tests/models.py
python_arango_ogm/db/tests/test_pao_discovery.py
python_arango_ogm/db/tests/test_pao_migration_builder.py
python_arango_ogm/db/tests/test_pao_migrator.py
python_arango_ogm/db/tests/test_pao_models.py
python_arango_ogm/notebooks/__init__.py
python_arango_ogm/notebooks/supernode.ipynb
python_arango_ogm/utils/f_range.py
python_arango_ogm/utils/iter_util.py
python_arango_ogm/utils/logger.py
python_arango_ogm/utils/math_util.py
python_arango_ogm/utils/md_util.py
python_arango_ogm/utils/singleton.py
python_arango_ogm/utils/str_util.py
python_arango_ogm/utils/test_f_range.py
python_arango_ogm/utils/test_math_util.py
python_arango_ogm/utils/test_str_util.py
python_arango_ogm/utils/time_util.py
python_arango_ogm/utils/type_util.py
python_arango_ogm-0.2.4.dist-info/METADATA
python_arango_ogm-0.2.4.dist-info/WHEEL
python_arango_ogm-0.2.4.dist-info/entry_points.txt
python_arango_ogm-0.2.4.dist-info/RECORD
