Metadata-Version: 2.1
Name: python-arango-ogm
Version: 0.2.4
Summary: Python-based package implementing an OGM framework for arango; built on top of python-arango.
Home-page: https://pypi.org/project/python-arango-ogm/
License: Unlicense
Author: Steven Miers
Author-email: steven.miers@gmail.com
Requires-Python: >=3.12.2,<4.0.0
Classifier: License :: OSI Approved
Classifier: Programming Language :: Python :: 3
Requires-Dist: jupyterlab (>=4.1.3,<5.0.0)
Requires-Dist: lorem-text (>=2.1,<3.0)
Requires-Dist: python-arango (>=7.9.1,<8.0.0)
Requires-Dist: python-dotenv (>=1.0.1,<2.0.0)
Requires-Dist: typer[all] (>=0.9.0,<0.10.0)
Project-URL: Documentation, https://tangledpath.github.io/python-arango-ogm
Project-URL: Repository, https://github.com/tangledpath/python-arango-ogm
